hysetter/__init__.py
hysetter/aoi.py
hysetter/cli.py
hysetter/exceptions.py
hysetter/forcing.py
hysetter/hysetter.py
hysetter/nid.py
hysetter/nlcd.py
hysetter/nwis.py
hysetter/print_versions.py
hysetter/rasters.py
hysetter/soil.py
hysetter/topo.py
hysetter/utils.py
hysetter-0.3.4.dist-info/METADATA
hysetter-0.3.4.dist-info/WHEEL
hysetter-0.3.4.dist-info/entry_points.txt
hysetter-0.3.4.dist-info/licenses/AUTHORS.md
hysetter-0.3.4.dist-info/licenses/LICENSE
hysetter-0.3.4.dist-info/RECORD
