Metadata-Version: 2.4
Name: hysetter
Version: 0.3.4
Summary: Subset hydroclimate data using HyRiver Over CONUS.
Project-URL: Changelog, https://hysetter.readthedocs.io/latest/CHANGELOG
Project-URL: CI, https://github.com/hyriver/hysetter/actions
Project-URL: Homepage, https://hysetter.readthedocs.io
Project-URL: Issues, https://github.com/hyriver/hysetter/issues
Author-email: Taher Chegini <cheginit@gmail.com>
License: MIT
License-File: AUTHORS.md
License-File: LICENSE
Classifier: Development Status :: 4 - Beta
Classifier: Intended Audience :: Science/Research
Classifier: License :: OSI Approved :: MIT License
Classifier: Operating System :: OS Independent
Classifier: Programming Language :: Python
Classifier: Programming Language :: Python :: 3 :: Only
Classifier: Programming Language :: Python :: 3.10
Classifier: Programming Language :: Python :: 3.11
Classifier: Programming Language :: Python :: 3.12
Classifier: Programming Language :: Python :: 3.13
Classifier: Topic :: Scientific/Engineering
Classifier: Topic :: Scientific/Engineering :: GIS
Classifier: Topic :: Scientific/Engineering :: Hydrology
Classifier: Typing :: Typed
Requires-Python: >=3.10
Requires-Dist: boto3
Requires-Dist: dask-expr
Requires-Dist: geopandas>=1
Requires-Dist: pandas>=2
Requires-Dist: planetary-computer
Requires-Dist: pyarrow>=1.0.1
Requires-Dist: pydantic>=2.7.1
Requires-Dist: pydaymet<0.20,>=0.19.4
Requires-Dist: pygeohydro<0.20,>=0.19
Requires-Dist: pygridmet<0.20,>=0.19
Requires-Dist: pynhd<0.20,>=0.19.4
Requires-Dist: pynldas2<0.20,>=0.19
Requires-Dist: pystac-client
Requires-Dist: pyyaml
Requires-Dist: rich-click>=1.8.2
Requires-Dist: seamless-3dep>=0.3
Requires-Dist: typing-extensions
Requires-Dist: xarray-spatial
Requires-Dist: xarray>=2024.5
Provides-Extra: dev
Requires-Dist: flox; extra == 'dev'
Requires-Dist: hydrosignatures<0.20,>=0.19; extra == 'dev'
Requires-Dist: ipykernel; extra == 'dev'
Requires-Dist: ipywidgets; extra == 'dev'
Requires-Dist: mapclassify; extra == 'dev'
Requires-Dist: matplotlib; extra == 'dev'
Requires-Dist: notebook; extra == 'dev'
Requires-Dist: numba; extra == 'dev'
Requires-Dist: numbagg; extra == 'dev'
Requires-Dist: pytest; extra == 'dev'
Requires-Dist: salib; extra == 'dev'
Requires-Dist: sceua; extra == 'dev'
Provides-Extra: docs
Requires-Dist: black; extra == 'docs'
Requires-Dist: mkdocs; extra == 'docs'
Requires-Dist: mkdocs-jupyter; extra == 'docs'
Requires-Dist: mkdocs-material; extra == 'docs'
Requires-Dist: mkdocs-minify-plugin; extra == 'docs'
Requires-Dist: mkdocstrings-python; extra == 'docs'
Provides-Extra: lint
Requires-Dist: codespell; extra == 'lint'
Requires-Dist: pre-commit; extra == 'lint'
Provides-Extra: test
Requires-Dist: coverage[toml]; extra == 'test'
Requires-Dist: pytest-cov; extra == 'test'
Requires-Dist: pytest-sugar; extra == 'test'
Provides-Extra: typecheck
Requires-Dist: pyright; extra == 'typecheck'
